{
  "chrome.storage.local": {
    "./plugins/blank/core.js": true,
    "./plugins/dummy/core.js": false,
    "./plugins/focus/core.js": false,
    "./plugins/force/core.js": false,
    "./plugins/new/core.js": false,
    "./plugins/next/core.js": false,
    "./plugins/previous/core.js": false,
    "./plugins/trash/core.js": false,
    "./plugins/unloaded/core.js": false,
    "./plugins/youtube/core.js": true,
    "audio": true,
    "battery": false,
    "click": "click.popup",
    "faqs": false,
    "favicon": true,
    "favicon-delay": 500,
    "force.hostnames": [],
    "form": true,
    "go-hidden": false,
    "idle": false,
    "idle-timeout": 300,
    "last-update": 1713841261750,
    "link.context": true,
    "log": false,
    "max.single.discard": 50,
    "memory-enabled": false,
    "memory-value": 60,
    "mode": "time-based",
    "notification.permission": true,
    "number": 8,
    "online": false,
    "page.context": false,
    "paused": false,
    "period": 8220,
    "pinned": true,
    "prepends": "💤",
    "simultaneous-jobs": 10,
    "startup-pinned": false,
    "startup-release-pinned": false,
    "startup-unpinned": false,
    "tab.context": true,
    "trash.period": 24,
    "trash.unloaded": false,
    "trash.whitelist-url": [],
    "whitelist": [
      "pastebin.com",
      "jsfiddle.net",
      "www.base64decode.org",
      "www.base64encode.org"
    ],
    "whitelist-url": []
  },
  "localStorage": {
    "click": "popup"
  }
}